scoring_matrices/lib.pyi
scoring_matrices/CMakeLists.txt
scoring_matrices/__init__.pxd
scoring_matrices/lib.abi3.so
scoring_matrices/lib.pxd
scoring_matrices/__init__.py
scoring_matrices/matrices.pxd
scoring_matrices/lib.pyx
scoring_matrices/.gitignore
scoring_matrices/py.typed
scoring_matrices/tests/__init__.py
scoring_matrices/tests/test_doctest.py
scoring_matrices/tests/test_scoring_matrix.py
scoring_matrices-0.3.4.dist-info/RECORD
scoring_matrices-0.3.4.dist-info/WHEEL
scoring_matrices-0.3.4.dist-info/METADATA
scoring_matrices-0.3.4.dist-info/licenses/COPYING
