Metadata-Version: 2.2
Name: scoring-matrices
Version: 0.3.4
Summary: Dependency free, Cython-compatible scoring matrices to use with biological sequences.
Keywords: bioinformatics,sequence,substitution,matrix,score
Author-Email: Martin Larralde <martin.larralde@embl.de>
License: MIT License
Classifier: Development Status :: 4 - Beta
Classifier: Intended Audience :: Developers
Classifier: Intended Audience :: Science/Research
Classifier: License :: OSI Approved :: MIT License
Classifier: Operating System :: OS Independent
Classifier: Programming Language :: C
Classifier: Programming Language :: Cython
Classifier: Programming Language :: Python :: 3.7
Classifier: Programming Language :: Python :: 3.8
Classifier: Programming Language :: Python :: 3.9
Classifier: Programming Language :: Python :: 3.10
Classifier: Programming Language :: Python :: 3.11
Classifier: Programming Language :: Python :: 3.12
Classifier: Programming Language :: Python :: 3.13
Classifier: Programming Language :: Python :: 3.14
Classifier: Programming Language :: Python :: Implementation :: CPython
Classifier: Programming Language :: Python :: Implementation :: PyPy
Classifier: Topic :: Scientific/Engineering :: Bio-Informatics
Classifier: Typing :: Typed
Project-URL: Documentation, https://scoring-matrices.readthedocs.io/en/stable/
Project-URL: Bug Tracker, https://github.com/althonos/scoring-matrices/issues
Project-URL: Changelog, https://github.com/althonos/scoring-matrices/blob/main/CHANGELOG.md
Project-URL: Coverage, https://codecov.io/gh/althonos/scoring-matrices/
Project-URL: Builds, https://github.com/althonos/scoring-matrices/actions
Project-URL: PyPI, https://pypi.org/project/scoring-matrices
Requires-Python: >=3.7
Provides-Extra: test
Requires-Dist: importlib-resources; python_version < "3.9" and extra == "test"
